mcp_toolgen/__init__.py
mcp_toolgen/mcp_toolgen.py
mcp_toolgen-0.1.3.dist-info/METADATA
mcp_toolgen-0.1.3.dist-info/WHEEL
mcp_toolgen-0.1.3.dist-info/entry_points.txt
mcp_toolgen-0.1.3.dist-info/licenses/LICENSE
mcp_toolgen-0.1.3.dist-info/RECORD
