Metadata-Version: 2.4
Name: mcp-toolgen
Version: 0.1.3
Summary: Generate OpenAI / Claude tool specs from GraphQL or gRPC.
Author: Noamski
License:                                  Apache License
License-File: LICENSE
Requires-Python: >=3.8
Requires-Dist: graphql-core>=3.2
Requires-Dist: protobuf>=4.25; extra == 'grpc'
Requires-Dist: requests>=2.31
Provides-Extra: dev
Requires-Dist: pytest>=7.0; extra == 'dev'
Provides-Extra: grpc
Requires-Dist: protobuf>=4.25; extra == 'grpc'
